Metadata-Version: 2.1
Name: mock-firestore-plus
Version: 0.12.4
Summary: In-memory implementation of Google Cloud Firestore for use in tests
Home-page: https://github.com/eddie/python-mock-firestore
Author: Matt Dowds
Classifier: Programming Language :: Python :: 3.6
Classifier: Programming Language :: Python :: 3.7
Classifier: Programming Language :: Python :: 3.8
Classifier: Programming Language :: Python :: 3.9
Classifier: Programming Language :: Python :: 3.10
Classifier: License :: OSI Approved :: MIT License
License-File: LICENSE
